theosocr/__init__.py
theosocr/ocr.py
theosocr/ocr_base64.py
theosocr-1.6.dist-info/METADATA
theosocr-1.6.dist-info/WHEEL
theosocr-1.6.dist-info/top_level.txt
theosocr-1.6.dist-info/RECORD
