Metadata-Version: 2.1
Name: theosocr
Version: 1.6
Summary: A simple Theos library using Theos API
Home-page: https://github.com/emretecno/theosocr
Author: theostekno
Author-email: theostekno@gmail.com
Classifier: Programming Language :: Python :: 3
Classifier: License :: OSI Approved :: MIT License
Classifier: Operating System :: OS Independent
Requires-Python: >=3.6
Requires-Dist: requests
